vpype_cfill-0.1.1.dist-info/METADATA
vpype_cfill-0.1.1.dist-info/WHEEL
vpype_cfill-0.1.1.dist-info/entry_points.txt
vpype_cfill-0.1.1.dist-info/licenses/LICENSE
vpype_cfill/__init__.py
vpype_cfill/vpype_cfill.py
vpype_cfill/vpype_cfill_rust.cp313-win_amd64.pyd
vpype_cfill-0.1.1.dist-info/RECORD
