Metadata-Version: 2.4
Name: vpype-cfill
Version: 0.1.1
Classifier: Development Status :: 3 - Alpha
Classifier: Intended Audience :: Developers
Classifier: License :: OSI Approved :: MIT License
Classifier: Programming Language :: Python :: 3
Classifier: Programming Language :: Python :: 3.9
Classifier: Programming Language :: Python :: 3.10
Classifier: Programming Language :: Python :: 3.11
Classifier: Programming Language :: Python :: 3.12
Classifier: Programming Language :: Python :: 3.13
Classifier: Programming Language :: Python :: 3.14
Classifier: Operating System :: POSIX :: Linux
Classifier: Operating System :: Microsoft :: Windows
Classifier: Operating System :: MacOS
Classifier: Programming Language :: Rust
Classifier: Topic :: Multimedia :: Graphics :: Graphics Conversion
Classifier: Topic :: Multimedia :: Graphics :: Editors :: Vector-Based
Requires-Dist: vpype>=1.9
Requires-Dist: click
Requires-Dist: numpy>=1.19.0
Requires-Dist: shapely>=1.7.0
License-File: LICENSE
Summary: A vpype extension for generating concentric fill patterns
Home-Page: https://github.com/map-blasterson/vpype-cfill
Author-email: Map Blasterson <m@blaster.mbelt.net>
License: MIT
Requires-Python: >=3.9
Project-URL: Homepage, https://github.com/map-blasterson/vpype-cfill
Project-URL: Repository, https://github.com/map-blasterson/vpype-cfill
